aio_wx_widgets/__init__.py
aio_wx_widgets/colors.py
aio_wx_widgets/const.py
aio_wx_widgets/controller.py
aio_wx_widgets/frame.py
aio_wx_widgets/py.typed
aio_wx_widgets/type_annotations.py
aio_wx_widgets/containers/__init__.py
aio_wx_widgets/containers/grid.py
aio_wx_widgets/containers/group.py
aio_wx_widgets/core/__init__.py
aio_wx_widgets/core/base_widget.py
aio_wx_widgets/core/binding.py
aio_wx_widgets/core/data_types.py
aio_wx_widgets/core/error_message.py
aio_wx_widgets/core/sizers.py
aio_wx_widgets/core/validators.py
aio_wx_widgets/panels/__init__.py
aio_wx_widgets/panels/panel.py
aio_wx_widgets/panels/splitter_panel.py
aio_wx_widgets/widgets/__init__.py
aio_wx_widgets/widgets/button.py
aio_wx_widgets/widgets/checkbox.py
aio_wx_widgets/widgets/image.py
aio_wx_widgets/widgets/labelled_item.py
aio_wx_widgets/widgets/select.py
aio_wx_widgets/widgets/text.py
aio_wx_widgets/widgets/text_entry.py
aio_wx_widgets/widgets/experimental/__init__.py
aio_wx_widgets/widgets/experimental/bullet_text.py
aio_wx_widgets/widgets/experimental/fixed_grid.py
aio_wx_widgets-1.3.10.dist-info/WHEEL
aio_wx_widgets-1.3.10.dist-info/METADATA
aio_wx_widgets-1.3.10.dist-info/RECORD
