Metadata-Version: 2.1
Name: aio_wx_widgets
Version: 1.3.10
Summary: aio_wx_widgets
Author: Sander Teunissen
Requires-Python: >=3.7
Requires-Dist: wxasync
Requires-Dist: wxpython
Requires-Dist: events
Requires-Dist: pylint ; extra == "dev"
Requires-Dist: nox ; extra == "dev"
Requires-Dist: pytest-cov ; extra == "dev"
Requires-Dist: coverage[toml]>=5.0.3 ; extra == "dev"
Requires-Dist: pre-commit ; extra == "dev"
Requires-Dist: typing-extensions ; extra == "dev" and ( python_version=='3.7')
Requires-Dist: pytest ; extra == "test"
Requires-Dist: pytest-asyncio ; extra == "test"
Requires-Dist: pytest-mock ; extra == "test"
Requires-Dist: mypy ; extra == "test"
Provides-Extra: dev
Provides-Extra: test
